[
    {
        "Название представления": "Екклесиаст",
        "Описание": "Изобретательные театрально-пластические аналогии библейским афоризмам",
        "Минимальная цена": "500",
        "Ближайшее время": "19:00",
        "Ближайшая дата": "01.06.2022",
        "Жанр": "Драма",
        "Рейтинг": "8.5",
        "Театр": "Большой театр кукол",
        "Ссылка на представление": "https://www.afisha.ru/performance/88347/",
        "Возрастное ограничение": "16+",
        "Адрес театра": "Некрасова, 10",
        "Продолжительность": "1 час 20 минут, без антракта",
        "Другие даты и время": -1
    },
    {
        "Название представления": "Губернатор",
        "Описание": "Зрелищный спектакль Андрея Могучего про механику тоталитаризма",
        "Минимальная цена": "500",
        "Ближайшее время": "19:00",
        "Ближайшая дата": "17.06.2022",
        "Жанр": "Драма",
        "Рейтинг": "8.6",
        "Театр": "БДТ",
        "Ссылка на представление": "https://www.afisha.ru/performance/190192/",
        "Возрастное ограничение": "18+",
        "Адрес театра": "наб. реки Фонтанки, 65",
        "Продолжительность": "1 час 45 минут, без антракта",
        "Другие даты и время": -1
    },
    {
        "Название представления": "Тихий Дон. Истоки. Берега",
        "Описание": "Восьмичасовой спектакль о казаках",
        "Минимальная цена": "1500",
        "Ближайшее время": "14:00",
        "Ближайшая дата": "03.05.2022",
        "Жанр": "Драма",
        "Рейтинг": "8.5",
        "Театр": "Мастерская",
        "Ссылка на представление": "https://www.afisha.ru/performance/94169/",
        "Возрастное ограничение": "16+",
        "Адрес театра": "Народная, 1",
        "Продолжительность": "4 часа, 1 антракт",
        "Другие даты и время": -1
    },
    {
        "Название представления": "Старосветские помещики",
        "Описание": "Пронзительное соло на двоих — безукоризненный дуэт Ирины Соколовой и Валерия Дьяченко",
        "Минимальная цена": "1000",
        "Ближайшее время": "19:00",
        "Ближайшая дата": "09.05.2022",
        "Жанр": "Драма",
        "Рейтинг": "7.5",
        "Театр": "ТЮЗ",
        "Ссылка на представление": "https://www.afisha.ru/performance/66048/",
        "Возрастное ограничение": "16+",
        "Адрес театра": "Пионерская пл., 1",
        "Продолжительность": "-1",
        "Другие даты и время": -1
    },
    {
        "Название представления": "Лето одного года",
        "Описание": "Алиса Фрейндлих и Олег Басилашвили с блеском и мужеством играют трагикомедию о старости и об уходе вообще",
        "Минимальная цена": "1000",
        "Ближайшее время": "19:00",
        "Ближайшая дата": "30.04.2022",
        "Жанр": "Драма",
        "Рейтинг": "8.9",
        "Театр": "БДТ",
        "Ссылка на представление": "https://www.afisha.ru/performance/82546/",
        "Возрастное ограничение": "12+",
        "Адрес театра": "наб. реки Фонтанки, 65",
        "Продолжительность": "3 часа, 1 антракт",
        "Другие даты и время": -1
    },
    {
        "Название представления": "Дни Турбиных",
        "Описание": "Камерная драма про глобальный политический перелом",
        "Минимальная цена": "1100",
        "Ближайшее время": "19:00",
        "Ближайшая дата": "28.04.2022",
        "Жанр": "Драма",
        "Рейтинг": "7.9",
        "Театр": "Мастерская",
        "Ссылка на представление": "https://www.afisha.ru/performance/95984/",
        "Возрастное ограничение": "16+",
        "Адрес театра": "Народная, 1",
        "Продолжительность": "-1",
        "Другие даты и время": -1
    },
    {
        "Название представления": "Пять вечеров",
        "Описание": "Пронзительная история о кризисе среднего возраста",
        "Минимальная цена": "400",
        "Ближайшее время": "19:00",
        "Ближайшая дата": "20.05.2022",
        "Жанр": "Драма",
        "Рейтинг": "7.8",
        "Театр": "Молодежный театр на Фонтанке",
        "Ссылка на представление": "https://www.afisha.ru/performance/68085/",
        "Возрастное ограничение": "16+",
        "Адрес театра": "наб. реки Фонтанки, 114",
        "Продолжительность": "2 часа 30 минут, 1 антракт",
        "Другие даты и время": -1
    },
    {
        "Название представления": "Идиот. 2012",
        "Описание": "Достоевский как повод порассуждать на тему «что такое хорошо и что такое плохо»",
        "Минимальная цена": "500",
        "Ближайшее время": "19:00",
        "Ближайшая дата": "06.05.2022",
        "Жанр": "Драма",
        "Рейтинг": "7.2",
        "Театр": "Молодежный театр на Фонтанке",
        "Ссылка на представление": "https://www.afisha.ru/performance/89931/",
        "Возрастное ограничение": "16+",
        "Адрес театра": "наб. реки Фонтанки, 114",
        "Продолжительность": "2 часа 50 минут, 1 антракт",
        "Другие даты и время": -1
    },
    {
        "Название представления": "Счастье мое...",
        "Описание": "Маленькая трагедия о разбитом сердце пионервожатой",
        "Минимальная цена": "900",
        "Ближайшее время": "19:00",
        "Ближайшая дата": "09.05.2022",
        "Жанр": "Драма",
        "Рейтинг": "7.3",
        "Театр": "Театр на Литейном",
        "Ссылка на представление": "https://www.afisha.ru/performance/74477/",
        "Возрастное ограничение": "16+",
        "Адрес театра": "Литейный просп., 51",
        "Продолжительность": "1 час 30 минут, без антракта",
        "Другие даты и время": -1
    },
    {
        "Название представления": "Звездная покатуха",
        "Описание": "Все классические номера «Лицедеев» в одном спектакле",
        "Минимальная цена": "500",
        "Ближайшее время": "18:00",
        "Ближайшая дата": "29.05.2022",
        "Жанр": "Комедия",
        "Рейтинг": "8.7",
        "Театр": "Лицедеи",
        "Ссылка на представление": "https://www.afisha.ru/performance/116779/",
        "Возрастное ограничение": "12+",
        "Адрес театра": "Льва Толстого, 9, ТРЦ «Толстой-сквер», 4 этаж",
        "Продолжительность": "2 часа, 1 антракт",
        "Другие даты и время": -1
    },
    {
        "Название представления": "Вий",
        "Описание": "Нешуточный хоррор для семейного просмотра",
        "Минимальная цена": "500",
        "Ближайшее время": "19:00",
        "Ближайшая дата": "06.05.2022",
        "Жанр": "Драма",
        "Рейтинг": "8.2",
        "Театр": "Большой театр кукол",
        "Ссылка на представление": "https://www.afisha.ru/performance/68503/",
        "Возрастное ограничение": "16+",
        "Адрес театра": "Некрасова, 10",
        "Продолжительность": "1 час 40 минут, 1 антракт",
        "Другие даты и время": -1
    },
    {
        "Название представления": "Билли Миллиган",
        "Описание": "Триллер про самого известного психа в истории",
        "Минимальная цена": "1600",
        "Ближайшее время": "19:00",
        "Ближайшая дата": "16.05.2022",
        "Жанр": "Драма",
        "Рейтинг": "5.2",
        "Театр": "Скороход",
        "Ссылка на представление": "https://www.afisha.ru/performance/118241/",
        "Возрастное ограничение": "18+",
        "Адрес театра": "Московский просп., 107, корп. 5, 4 этаж",
        "Продолжительность": "4 часа, 2 антракта",
        "Другие даты и время": -1
    },
    {
        "Название представления": "Малые супружеские преступления",
        "Описание": "Камерный семейный детектив с изящными афоризмами",
        "Минимальная цена": "1500",
        "Ближайшее время": "19:00",
        "Ближайшая дата": "04.05.2022",
        "Жанр": "Драма",
        "Рейтинг": "7.3",
        "Театр": "Русская антреприза им. Андрея Миронова",
        "Ссылка на представление": "https://www.afisha.ru/performance/67762/",
        "Возрастное ограничение": "14+",
        "Адрес театра": "Большой просп. П.С., 75/35",
        "Продолжительность": "1 час 30 минут, без антракта",
        "Другие даты и время": -1
    },
    {
        "Название представления": "БалБесы",
        "Описание": "Гомерически смешной капустник для взрослых по сказкам Пушкина",
        "Минимальная цена": "1200",
        "Ближайшее время": "19:00",
        "Ближайшая дата": "27.04.2022",
        "Жанр": "Комедия",
        "Рейтинг": "6.9",
        "Театр": "За Черной речкой",
        "Ссылка на представление": "https://www.afisha.ru/performance/67655/",
        "Возрастное ограничение": "16+",
        "Адрес театра": "Богатырский просп., 4",
        "Продолжительность": "1 час, 40 минут, без антракта",
        "Другие даты и время": -1
    },
    {
        "Название представления": "Башлачев. Человек поющий",
        "Описание": "Молодые питерские актеры играют этюды по мотивам песен Башлачева",
        "Минимальная цена": "1300",
        "Ближайшее время": "19:00",
        "Ближайшая дата": "11.05.2022",
        "Жанр": "Драма",
        "Рейтинг": "8.3",
        "Театр": "Большой театр кукол",
        "Ссылка на представление": "https://www.afisha.ru/performance/83295/",
        "Возрастное ограничение": "16+",
        "Адрес театра": "Некрасова, 10",
        "Продолжительность": "-1",
        "Другие даты и время": -1
    },
    {
        "Название представления": "Мадам Бовари",
        "Описание": "Мифологического масштаба театральная история об истине страстей",
        "Минимальная цена": "1500",
        "Ближайшее время": "19:00",
        "Ближайшая дата": "22.05.2022",
        "Жанр": "Драма",
        "Рейтинг": "7.4",
        "Театр": "Русская антреприза им. Андрея Миронова",
        "Ссылка на представление": "https://www.afisha.ru/performance/97009/",
        "Возрастное ограничение": "16+",
        "Адрес театра": "Большой просп. П.С., 75/35",
        "Продолжительность": "3 часа 30 минут, 1 антракт",
        "Другие даты и время": -1
    },
    {
        "Название представления": "На дне",
        "Описание": "Олигофрены и параноики в актуальной интерпретации Горького",
        "Минимальная цена": "900",
        "Ближайшее время": "19:00",
        "Ближайшая дата": "25.04.2022",
        "Жанр": "Драма",
        "Рейтинг": "7.1",
        "Театр": "Небольшой драматический театр",
        "Ссылка на представление": "https://www.afisha.ru/performance/67782/",
        "Возрастное ограничение": "18+",
        "Адрес театра": "просп. КИМа, 6",
        "Продолжительность": "-1",
        "Другие даты и время": -1
    },
    {
        "Название представления": "Бедные люди",
        "Описание": "Достоевский, адаптированный для школьников с уникальным артистом Валерием Дьяченко",
        "Минимальная цена": "1000",
        "Ближайшее время": "19:00",
        "Ближайшая дата": "06.05.2022",
        "Жанр": "Драма",
        "Рейтинг": "7.4",
        "Театр": "ТЮЗ",
        "Ссылка на представление": "https://www.afisha.ru/performance/71206/",
        "Возрастное ограничение": "16+",
        "Адрес театра": "Пионерская пл., 1",
        "Продолжительность": "2 часа 15 минут, 1 антракт",
        "Другие даты и время": -1
    },
    {
        "Название представления": "Мы",
        "Описание": "Молодежный спектакль по Замятину про то, как общество превращается в толпу",
        "Минимальная цена": "500",
        "Ближайшее время": "19:00",
        "Ближайшая дата": "27.05.2022",
        "Жанр": "Драма",
        "Рейтинг": "6.1",
        "Театр": "Большой театр кукол",
        "Ссылка на представление": "https://www.afisha.ru/performance/78575/",
        "Возрастное ограничение": "16+",
        "Адрес театра": "Некрасова, 10",
        "Продолжительность": "2 часа, 1 антракт",
        "Другие даты и время": -1
    },
    {
        "Название представления": "Поминальная молитва",
        "Описание": "Еще один «Тевье-молочник», зрелищный и предсказуемый",
        "Минимальная цена": "800",
        "Ближайшее время": "19:00",
        "Ближайшая дата": "01.05.2022",
        "Жанр": "Драма",
        "Рейтинг": "9",
        "Театр": "Театр на Литейном",
        "Ссылка на представление": "https://www.afisha.ru/performance/98328/",
        "Возрастное ограничение": "16+",
        "Адрес театра": "Литейный просп., 51",
        "Продолжительность": "3 часа 30 минут, 1 антракт",
        "Другие даты и время": -1
    },
    {
        "Название представления": "Школа",
        "Описание": "Ироничное сочинение на тему, как я провел школьные годы",
        "Минимальная цена": "400",
        "Ближайшее время": "19:30",
        "Ближайшая дата": "20.05.2022",
        "Жанр": "Драма",
        "Рейтинг": "7.9",
        "Театр": "Театр-фестиваль «Балтийский дом»",
        "Ссылка на представление": "https://www.afisha.ru/performance/89678/",
        "Возрастное ограничение": "18+",
        "Адрес театра": "Александровский парк, 4",
        "Продолжительность": "-1",
        "Другие даты и время": -1
    },
    {
        "Название представления": "Лерка",
        "Описание": "Смешная и жуткая история девчонки с нашего двора по текстам Василия Сигарева",
        "Минимальная цена": "400",
        "Ближайшее время": "19:00",
        "Ближайшая дата": "04.05.2022",
        "Жанр": "Драма",
        "Рейтинг": "5.5",
        "Театр": "Театр-фестиваль «Балтийский дом»",
        "Ссылка на представление": "https://www.afisha.ru/performance/78407/",
        "Возрастное ограничение": "18+",
        "Адрес театра": "Александровский парк, 4",
        "Продолжительность": "-1",
        "Другие даты и время": -1
    },
    {
        "Название представления": "Буря",
        "Описание": "Умный трагифарс от режиссера Морфова, фокусы с пространством от художника Капелюша",
        "Минимальная цена": "300",
        "Ближайшее время": "19:00",
        "Ближайшая дата": "16.05.2022",
        "Жанр": "Драма",
        "Рейтинг": "7.2",
        "Театр": "Театр им. Комиссаржевской",
        "Ссылка на представление": "https://www.afisha.ru/performance/65972/",
        "Возрастное ограничение": "16+",
        "Адрес театра": "Итальянская, 19",
        "Продолжительность": "-1",
        "Другие даты и время": -1
    },
    {
        "Название представления": "Графоман",
        "Описание": "Комплексы и лирика советских 70-х по стихам и прозе Александра Володина",
        "Минимальная цена": "300",
        "Ближайшее время": "19:00",
        "Ближайшая дата": "29.05.2022",
        "Жанр": "Драма",
        "Рейтинг": "7.9",
        "Театр": "Театр им. Комиссаржевской",
        "Ссылка на представление": "https://www.afisha.ru/performance/99034/",
        "Возрастное ограничение": "18+",
        "Адрес театра": "Итальянская, 19",
        "Продолжительность": "-1",
        "Другие даты и время": -1
    },
    {
        "Название представления": "Скамейка",
        "Описание": "Не самая банальная советская мелодрама, сыгранная как французский шансон",
        "Минимальная цена": "500",
        "Ближайшее время": "19:00",
        "Ближайшая дата": "17.05.2022",
        "Жанр": "Драма",
        "Рейтинг": "7.4",
        "Театр": "Концертный зал в здании Екатерининского собрания",
        "Ссылка на представление": "https://www.afisha.ru/performance/77005/",
        "Возрастное ограничение": "12+",
        "Адрес театра": "наб. канала Грибоедова, 88–90",
        "Продолжительность": "1 час 40 минут, без антракта",
        "Другие даты и время": -1
    },
    {
        "Название представления": "Что делать",
        "Описание": "Разговорная антиутопия Андрея Могучего по Чернышевскому",
        "Минимальная цена": "500",
        "Ближайшее время": "19:00",
        "Ближайшая дата": "04.10.2022",
        "Жанр": "Драма",
        "Рейтинг": "6.2",
        "Театр": "БДТ",
        "Ссылка на представление": "https://www.afisha.ru/performance/101454/",
        "Возрастное ограничение": "16+",
        "Адрес театра": "наб. реки Фонтанки, 65",
        "Продолжительность": "1 час 35 минут, без антракта",
        "Другие даты и время": -1
    },
    {
        "Название представления": "Двое на качелях",
        "Описание": "Муки и радости сегодняшних Дидоны и Энея под музыку Перселла",
        "Минимальная цена": "500",
        "Ближайшее время": "19:00",
        "Ближайшая дата": "24.04.2022",
        "Жанр": "Драма",
        "Рейтинг": "5.2",
        "Театр": "Приют комедианта",
        "Ссылка на представление": "https://www.afisha.ru/performance/67910/",
        "Возрастное ограничение": "16+",
        "Адрес театра": "Садовая, 27/9",
        "Продолжительность": "2 часа 40 минут, 1 антракт",
        "Другие даты и время": -1
    },
    {
        "Название представления": "Zholdak Dreams: похитители чувств",
        "Описание": "Мафиози и космические пираты перекраивают «Слугу двух господ»",
        "Минимальная цена": "500",
        "Ближайшее время": "19:00",
        "Ближайшая дата": "31.05.2022",
        "Жанр": "Драма",
        "Рейтинг": "5.8",
        "Театр": "Каменноостровский театр",
        "Ссылка на представление": "https://www.afisha.ru/performance/103720/",
        "Возрастное ограничение": "18+",
        "Адрес театра": "пл. Старого театра, 13",
        "Продолжительность": "3 часа, 1 антракт",
        "Другие даты и время": -1
    },
    {
        "Название представления": "Колобок",
        "Описание": "Выпускники Руслана Кудашова играют с детсадовским залом и с элементами собственной одежды",
        "Минимальная цена": "600",
        "Ближайшее время": "11:30",
        "Ближайшая дата": "11.06.2022",
        "Жанр": "Кукольный спектакль",
        "Рейтинг": "7",
        "Театр": "Большой театр кукол",
        "Ссылка на представление": "https://www.afisha.ru/performance/81557/",
        "Возрастное ограничение": "0+",
        "Адрес театра": "Некрасова, 10",
        "Продолжительность": "-1",
        "Другие даты и время": -1
    },
    {
        "Название представления": "Голодранцы и аристократы",
        "Описание": "Неаполитанская комедия с переодеваниями",
        "Минимальная цена": "500",
        "Ближайшее время": "19:00",
        "Ближайшая дата": "21.06.2022",
        "Жанр": "Комедия",
        "Рейтинг": "6.3",
        "Театр": "Театр комедии им. Акимова",
        "Ссылка на представление": "https://www.afisha.ru/performance/76709/",
        "Возрастное ограничение": "12+",
        "Адрес театра": "Невский просп., 56",
        "Продолжительность": "-1",
        "Другие даты и время": -1
    },
    {
        "Название представления": "Смерть Тарелкина",
        "Описание": "Футуристическая кибертрагикомедия Оскараса Коршуноваса",
        "Минимальная цена": "500",
        "Ближайшее время": "19:00",
        "Ближайшая дата": "13.05.2022",
        "Жанр": "Драма",
        "Рейтинг": "6.4",
        "Театр": "Театр-фестиваль «Балтийский дом»",
        "Ссылка на представление": "https://www.afisha.ru/performance/245157/",
        "Возрастное ограничение": "16+",
        "Адрес театра": "Александровский парк, 4",
        "Продолжительность": "3 часа, 1 антракт",
        "Другие даты и время": -1
    },
    {
        "Название представления": "Мыльные ангелы",
        "Описание": "Темпераментный экзерсис режиссера Александра Морфова про то, что жизнь есть цирк",
        "Минимальная цена": "300",
        "Ближайшее время": "19:00",
        "Ближайшая дата": "21.05.2022",
        "Жанр": "Драма",
        "Рейтинг": "4.4",
        "Театр": "Театр им. Комиссаржевской",
        "Ссылка на представление": "https://www.afisha.ru/performance/79166/",
        "Возрастное ограничение": "16+",
        "Адрес театра": "Итальянская, 19",
        "Продолжительность": "-1",
        "Другие даты и время": -1
    },
    {
        "Название представления": "Я боюсь любви",
        "Описание": "Качественный вербатим серьезного драматурга в постановке молодого режиссера",
        "Минимальная цена": "400",
        "Ближайшее время": "19:00",
        "Ближайшая дата": "20.06.2022",
        "Жанр": "Драма",
        "Рейтинг": "6",
        "Театр": "Театр им. Ленсовета",
        "Ссылка на представление": "https://www.afisha.ru/performance/82222/",
        "Возрастное ограничение": "16+",
        "Адрес театра": "Владимирский просп., 12",
        "Продолжительность": "1 час 30 минут, без антракта",
        "Другие даты и время": -1
    },
    {
        "Название представления": "Маленький принц",
        "Описание": "Экзюпери для младших школьников — нарядный и сентиментальный",
        "Минимальная цена": "500",
        "Ближайшее время": "11:30",
        "Ближайшая дата": "01.05.2022",
        "Жанр": "Кукольный спектакль",
        "Рейтинг": "5.1",
        "Театр": "Большой театр кукол",
        "Ссылка на представление": "https://www.afisha.ru/performance/74266/",
        "Возрастное ограничение": "6+",
        "Адрес театра": "Некрасова, 10",
        "Продолжительность": "1 час, без антракта",
        "Другие даты и время": -1
    },
    {
        "Название представления": "Дама с собачкой",
        "Описание": "Чеховская история без ложной романтики: от пошлости до любви – один шаг, но его еще надо сделать",
        "Минимальная цена": "1000",
        "Ближайшее время": "18:00",
        "Ближайшая дата": "05.06.2022",
        "Жанр": "Драма",
        "Рейтинг": "4.9",
        "Театр": "БДТ",
        "Ссылка на представление": "https://www.afisha.ru/performance/74894/",
        "Возрастное ограничение": "16+",
        "Адрес театра": "наб. реки Фонтанки, 65",
        "Продолжительность": "2 часа 35 минут, 1 антракт",
        "Другие даты и время": -1
    },
    {
        "Название представления": "Бармалей",
        "Описание": "Гимн заботливым и режиссерски одаренным бабушкам",
        "Минимальная цена": "550",
        "Ближайшее время": "11:00",
        "Ближайшая дата": "21.05.2022",
        "Жанр": "Кукольный спектакль",
        "Рейтинг": "6.3",
        "Театр": "Бродячая собачка",
        "Ссылка на представление": "https://www.afisha.ru/performance/73038/",
        "Возрастное ограничение": "0+",
        "Адрес театра": "просп. Стачек, 59",
        "Продолжительность": " ",
        "Другие даты и время": -1
    },
    {
        "Название представления": "Однажды в Эльсиноре. Гамлет",
        "Описание": "Секс, бокс, рок-н-ролл — в переводе Пастернака",
        "Минимальная цена": "500",
        "Ближайшее время": "19:00",
        "Ближайшая дата": "28.05.2022",
        "Жанр": "Драма",
        "Рейтинг": "5.2",
        "Театр": "Мастерская",
        "Ссылка на представление": "https://www.afisha.ru/performance/98674/",
        "Возрастное ограничение": "16+",
        "Адрес театра": "Народная, 1",
        "Продолжительность": "-1",
        "Другие даты и время": -1
    },
    {
        "Название представления": "Старомодная комедия",
        "Описание": "Советская лирическая комедия для двух почтенных артистов",
        "Минимальная цена": "500",
        "Ближайшее время": "19:00",
        "Ближайшая дата": "09.05.2022",
        "Жанр": "Драма",
        "Рейтинг": "4.6",
        "Театр": "Приют комедианта",
        "Ссылка на представление": "https://www.afisha.ru/performance/104925/",
        "Возрастное ограничение": "16+",
        "Адрес театра": "Садовая, 27/9",
        "Продолжительность": "2 часа 15 минут, 1 антракт",
        "Другие даты и время": -1
    },
    {
        "Название представления": "Три толстяка. Эпизод 1. Восстание",
        "Описание": "Могучий строит коммунизм",
        "Минимальная цена": "500",
        "Ближайшее время": "19:00",
        "Ближайшая дата": "25.05.2022",
        "Жанр": "Драма",
        "Рейтинг": "3.1",
        "Театр": "БДТ",
        "Ссылка на представление": "https://www.afisha.ru/performance/203746/",
        "Возрастное ограничение": "12+",
        "Адрес театра": "наб. реки Фонтанки, 65",
        "Продолжительность": "2 часа, без антракта",
        "Другие даты и время": -1
    },
    {
        "Название представления": "Ай-яй ревю",
        "Описание": "Лучшие номера театра «Лицедеи», начиная с полунинских времен",
        "Минимальная цена": "500",
        "Ближайшее время": "18:00",
        "Ближайшая дата": "15.05.2022",
        "Жанр": "Комедия",
        "Рейтинг": "2.7",
        "Театр": "Лицедеи",
        "Ссылка на представление": "https://www.afisha.ru/performance/81583/",
        "Возрастное ограничение": "12+",
        "Адрес театра": "Льва Толстого, 9, ТРЦ «Толстой-сквер», 4 этаж",
        "Продолжительность": "1 час 40 минут, без антракта",
        "Другие даты и время": -1
    },
    {
        "Название представления": "Мертвые души",
        "Описание": "Спектакль-расследование от ученика Юрия Бутусова",
        "Минимальная цена": "600",
        "Ближайшее время": "19:00",
        "Ближайшая дата": "27.04.2022",
        "Жанр": "Драма",
        "Рейтинг": "6.6",
        "Театр": "Театр им. Ленсовета",
        "Ссылка на представление": "https://www.afisha.ru/performance/207450/",
        "Возрастное ограничение": "16+",
        "Адрес театра": "Владимирский просп., 12",
        "Продолжительность": "2 часа 40 минут, 1 антракт",
        "Другие даты и время": -1
    },
    {
        "Название представления": "Три толстяка. Эпизод 2. Железное сердце",
        "Описание": "Мир после апокалипсиса во второй части сказки-антиутопии Андрея Могучего",
        "Минимальная цена": "500",
        "Ближайшее время": "19:00",
        "Ближайшая дата": "26.05.2022",
        "Жанр": "Драма",
        "Рейтинг": "2.8",
        "Театр": "БДТ",
        "Ссылка на представление": "https://www.afisha.ru/performance/203747/",
        "Возрастное ограничение": "12+",
        "Адрес театра": "наб. реки Фонтанки, 65",
        "Продолжительность": "2 часа, без антракта",
        "Другие даты и время": -1
    },
    {
        "Название представления": "Калека с острова Инишмаан",
        "Описание": "Артисты БДТ играют востребованную комедию МакДонаха",
        "Минимальная цена": "500",
        "Ближайшее время": "19:00",
        "Ближайшая дата": "07.05.2022",
        "Жанр": "Драма",
        "Рейтинг": "7.9",
        "Театр": "Каменноостровский театр",
        "Ссылка на представление": "https://www.afisha.ru/performance/94152/",
        "Возрастное ограничение": "18+",
        "Адрес театра": "пл. Старого театра, 13",
        "Продолжительность": "3 часа, 1 антракт",
        "Другие даты и время": -1
    },
    {
        "Название представления": "Todd",
        "Описание": "Масштабная страшилка от группы «Король и Шут»",
        "Минимальная цена": "2000",
        "Ближайшее время": "15:00",
        "Ближайшая дата": "04.06.2022",
        "Жанр": "Музыкальный",
        "Рейтинг": "6.6",
        "Театр": "Октябрьский",
        "Ссылка на представление": "https://www.afisha.ru/performance/91509/",
        "Возрастное ограничение": "12+",
        "Адрес театра": -1,
        "Продолжительность": "-1",
        "Другие даты и время": -1
    },
    {
        "Название представления": "Три сестры",
        "Описание": "Экзальтированное зрелище по поводу пьесы Чехова",
        "Минимальная цена": "600",
        "Ближайшее время": "18:00",
        "Ближайшая дата": "21.05.2022",
        "Жанр": "Драма",
        "Рейтинг": "8.4",
        "Театр": "Театр им. Ленсовета",
        "Ссылка на представление": "https://www.afisha.ru/performance/96363/",
        "Возрастное ограничение": "16+",
        "Адрес театра": "Владимирский просп., 12",
        "Продолжительность": "4 часа 40 минут, 2 антракта",
        "Другие даты и время": -1
    },
    {
        "Название представления": "Наш городок",
        "Описание": "Истории несуществовавших жителей несуществовавшего города",
        "Минимальная цена": "500",
        "Ближайшее время": "19:00",
        "Ближайшая дата": "05.05.2022",
        "Жанр": "Драма",
        "Рейтинг": "6.5",
        "Театр": "Молодежный театр на Фонтанке",
        "Ссылка на представление": "https://www.afisha.ru/performance/100332/",
        "Возрастное ограничение": "16+",
        "Адрес театра": "наб. реки Фонтанки, 114",
        "Продолжительность": "2 часа 55 минут",
        "Другие даты и время": -1
    },
    {
        "Название представления": "Слава",
        "Описание": "Константин Богомолов делает советский мюзикл с Ниной Усатовой",
        "Минимальная цена": "500",
        "Ближайшее время": "19:00",
        "Ближайшая дата": "27.05.2022",
        "Жанр": "Драма",
        "Рейтинг": "7",
        "Театр": "БДТ",
        "Ссылка на представление": "https://www.afisha.ru/performance/204845/",
        "Возрастное ограничение": "12+",
        "Адрес театра": "наб. реки Фонтанки, 65",
        "Продолжительность": "2 часа 10 минут, 1 антракт",
        "Другие даты и время": -1
    },
    {
        "Название представления": "Школа налогоплательщиков",
        "Описание": "Антикризисная комедия",
        "Минимальная цена": "400",
        "Ближайшее время": "18:00",
        "Ближайшая дата": "03.05.2022",
        "Жанр": "Комедия",
        "Рейтинг": "7.8",
        "Театр": "Молодежный театр на Фонтанке",
        "Ссылка на представление": "https://www.afisha.ru/performance/78906/",
        "Возрастное ограничение": "16+",
        "Адрес театра": "наб. реки Фонтанки, 114",
        "Продолжительность": "3 часа 30 минут, 2 антракта",
        "Другие даты и время": -1
    },
    {
        "Название представления": "Идиот. Возвращение. Четыре сцены из жизни Льва Николаевича Мышкина",
        "Описание": "Ученики Григория Козлова играют начало романа Достоевского",
        "Минимальная цена": "900",
        "Ближайшее время": "18:00",
        "Ближайшая дата": "02.05.2022",
        "Жанр": "Драма",
        "Рейтинг": "7.6",
        "Театр": "Мастерская",
        "Ссылка на представление": "https://www.afisha.ru/performance/80617/",
        "Возрастное ограничение": "16+",
        "Адрес театра": "Народная, 1",
        "Продолжительность": "-1",
        "Другие даты и время": -1
    },
    {
        "Название представления": "Задержанный",
        "Описание": "Бархоппинг по мотивам рассказов Довлатова",
        "Минимальная цена": "2000",
        "Ближайшее время": "18:00",
        "Ближайшая дата": "24.04.2022",
        "Жанр": "Моноспектакль",
        "Рейтинг": "7.6",
        "Театр": "Сайгон",
        "Ссылка на представление": "https://www.afisha.ru/performance/158572/",
        "Возрастное ограничение": "18+",
        "Адрес театра": "Рубинштейна, 1",
        "Продолжительность": "-1",
        "Другие даты и время": -1
    },
    {
        "Название представления": "Стакан воды",
        "Описание": "Королевские интриги вокруг хорошенького капитана.",
        "Минимальная цена": "400",
        "Ближайшее время": "19:00",
        "Ближайшая дата": "12.05.2022",
        "Жанр": "Драма",
        "Рейтинг": "7.9",
        "Театр": "Молодежный театр на Фонтанке",
        "Ссылка на представление": "https://www.afisha.ru/performance/66163/",
        "Возрастное ограничение": "16+",
        "Адрес театра": "наб. реки Фонтанки, 114",
        "Продолжительность": "3 часа 30 минут, 1 антракт",
        "Другие даты и время": -1
    },
    {
        "Название представления": "Три сестры",
        "Описание": "«Три сестры» двадцать лет спустя",
        "Минимальная цена": "500",
        "Ближайшее время": "19:00",
        "Ближайшая дата": "16.06.2022",
        "Жанр": "Драма",
        "Рейтинг": "7.1",
        "Театр": "БДТ",
        "Ссылка на представление": "https://www.afisha.ru/performance/190346/",
        "Возрастное ограничение": "16+",
        "Адрес театра": "наб. реки Фонтанки, 65",
        "Продолжительность": "3 часа 30 минут, 1 антракт",
        "Другие даты и время": -1
    },
    {
        "Название представления": "Турандот",
        "Описание": "Остроумная рэп-интерпретация пьесы Карла Гоцци",
        "Минимальная цена": "500",
        "Ближайшее время": "19:00",
        "Ближайшая дата": "12.05.2022",
        "Жанр": "Драма",
        "Рейтинг": "5.5",
        "Театр": "Мастерская",
        "Ссылка на представление": "https://www.afisha.ru/performance/95850/",
        "Возрастное ограничение": "16+",
        "Адрес театра": -1,
        "Продолжительность": "3 часа 40 минут, 1 антракт",
        "Другие даты и время": -1
    },
    {
        "Название представления": "Семейный портрет",
        "Описание": "Горький, упрощенный до сериальной истории",
        "Минимальная цена": "900",
        "Ближайшее время": "19:00",
        "Ближайшая дата": "25.05.2022",
        "Жанр": "Драма",
        "Рейтинг": "7.9",
        "Театр": "Театр на Литейном",
        "Ссылка на представление": "https://www.afisha.ru/performance/87640/",
        "Возрастное ограничение": "16+",
        "Адрес театра": "Литейный просп., 51",
        "Продолжительность": "2 часа 40 минут, 1 антракт",
        "Другие даты и время": -1
    },
    {
        "Название представления": "Братья Карамазовы",
        "Описание": "Незатейливое разыгрывание диалогов из романа Достоевского",
        "Минимальная цена": "700",
        "Ближайшее время": "17:00",
        "Ближайшая дата": "22.05.2022",
        "Жанр": "Драма",
        "Рейтинг": "7.2",
        "Театр": "Мастерская",
        "Ссылка на представление": "https://www.afisha.ru/performance/102359/",
        "Возрастное ограничение": "16+",
        "Адрес театра": "Народная, 1",
        "Продолжительность": "-1",
        "Другие даты и время": -1
    },
    {
        "Название представления": "Иранская конференция",
        "Описание": "Десять взглядов на современную действительность",
        "Минимальная цена": "1500",
        "Ближайшее время": "19:00",
        "Ближайшая дата": "01.05.2022",
        "Жанр": "Драма",
        "Рейтинг": "6.2",
        "Театр": "Скороход",
        "Ссылка на представление": "https://www.afisha.ru/performance/229847/",
        "Возрастное ограничение": "18+",
        "Адрес театра": "Московский просп., 107, корп. 5, 4 этаж",
        "Продолжительность": "2 часа 15 минут, 1 антракт",
        "Другие даты и время": -1
    },
    {
        "Название представления": "Преступление и наказание",
        "Описание": "Внимательное прочтение романа на сцене",
        "Минимальная цена": "700",
        "Ближайшее время": "19:00",
        "Ближайшая дата": "09.06.2022",
        "Жанр": "Драма",
        "Рейтинг": "6.7",
        "Театр": "Приют комедианта",
        "Ссылка на представление": "https://www.afisha.ru/performance/207448/",
        "Возрастное ограничение": "18+",
        "Адрес театра": "Садовая, 27/9",
        "Продолжительность": "3 часа 30 минут, 2 антракта",
        "Другие даты и время": -1
    },
    {
        "Название представления": "Детектор лжи",
        "Описание": "Провинциальный анекдот с участием гипнотизера",
        "Минимальная цена": "1000",
        "Ближайшее время": "19:00",
        "Ближайшая дата": "28.05.2022",
        "Жанр": "Драма",
        "Рейтинг": "5.9",
        "Театр": "Русская антреприза им. Андрея Миронова",
        "Ссылка на представление": "https://www.afisha.ru/performance/74887/",
        "Возрастное ограничение": "16+",
        "Адрес театра": "Большой просп. П.С., 75/35",
        "Продолжительность": "2 часа, 1 антракт",
        "Другие даты и время": -1
    },
    {
        "Название представления": "Любовь после жизни",
        "Описание": "Трагикомедия о любви в театре, в Испании, в 1938 году",
        "Минимальная цена": "400",
        "Ближайшее время": "18:00",
        "Ближайшая дата": "30.04.2022",
        "Жанр": "Драма",
        "Рейтинг": "5.8",
        "Театр": "Молодежный театр на Фонтанке",
        "Ссылка на представление": "https://www.afisha.ru/performance/90451/",
        "Возрастное ограничение": "18+",
        "Адрес театра": "наб. реки Фонтанки, 114",
        "Продолжительность": "2 часа 30 минут, 1 антракт",
        "Другие даты и время": -1
    },
    {
        "Название представления": "Человек из Подольска",
        "Описание": "Михаил Бычков ставит самую модную пьесу последних лет",
        "Минимальная цена": "500",
        "Ближайшее время": "19:00",
        "Ближайшая дата": "14.06.2022",
        "Жанр": "Комедия",
        "Рейтинг": "6.1",
        "Театр": "Приют комедианта",
        "Ссылка на представление": "https://www.afisha.ru/performance/205524/",
        "Возрастное ограничение": "18+",
        "Адрес театра": "Садовая, 27/9",
        "Продолжительность": "1 час 40 минут, без антракта",
        "Другие даты и время": -1
    },
    {
        "Название представления": "Золушка",
        "Описание": "Лучший российский оперный спектакль по версии «Золотой маски» конца нулевых",
        "Минимальная цена": "400",
        "Ближайшее время": "19:00",
        "Ближайшая дата": "21.05.2022",
        "Жанр": "Опера",
        "Рейтинг": "6.5",
        "Театр": "Зазеркалье",
        "Ссылка на представление": "https://www.afisha.ru/performance/77506/",
        "Возрастное ограничение": "16+",
        "Адрес театра": "Рубинштейна, 13",
        "Продолжительность": "-1",
        "Другие даты и время": -1
    },
    {
        "Название представления": "Иов",
        "Описание": "Еврейская сага",
        "Минимальная цена": "400",
        "Ближайшее время": "19:00",
        "Ближайшая дата": "19.05.2022",
        "Жанр": "Драма",
        "Рейтинг": "6.3",
        "Театр": "Молодежный театр на Фонтанке",
        "Ссылка на представление": "https://www.afisha.ru/performance/77813/",
        "Возрастное ограничение": "16+",
        "Адрес театра": "наб. реки Фонтанки, 114",
        "Продолжительность": "3 часа 30 минут, 1 антракт",
        "Другие даты и время": -1
    },
    {
        "Название представления": "Детский альбом",
        "Описание": "Гастроли петербургского театра «Зазеркалье» в Большом театре",
        "Минимальная цена": "400",
        "Ближайшее время": "19:00",
        "Ближайшая дата": "14.05.2022",
        "Жанр": "Опера",
        "Рейтинг": "6.9",
        "Театр": "Зазеркалье",
        "Ссылка на представление": "https://www.afisha.ru/performance/66336/",
        "Возрастное ограничение": "6+",
        "Адрес театра": "Рубинштейна, 13",
        "Продолжительность": "-1",
        "Другие даты и время": -1
    },
    {
        "Название представления": "У ковчега в восемь",
        "Описание": "История великого потопа для тинэджеров: глазами пингвинов",
        "Минимальная цена": "990",
        "Ближайшее время": "15:00",
        "Ближайшая дата": "15.05.2022",
        "Жанр": "Драма",
        "Рейтинг": "5.2",
        "Театр": "КДЦ «Московский»",
        "Ссылка на представление": "https://www.afisha.ru/performance/83123/",
        "Возрастное ограничение": "12+",
        "Адрес театра": "Московский просп., 152",
        "Продолжительность": "-1",
        "Другие даты и время": -1
    },
    {
        "Название представления": "Книга Иова",
        "Описание": "Актеры кукольного театра играют трагедию по мотивам библейского сюжета",
        "Минимальная цена": "400",
        "Ближайшее время": "19:00",
        "Ближайшая дата": "26.05.2022",
        "Жанр": "Драма",
        "Рейтинг": "4.9",
        "Театр": "Большой театр кукол",
        "Ссылка на представление": "https://www.afisha.ru/performance/100462/",
        "Возрастное ограничение": "16+",
        "Адрес театра": "Некрасова, 10",
        "Продолжительность": "1 час 5 минут",
        "Другие даты и время": -1
    },
    {
        "Название представления": "Высоцкий. Requiem",
        "Описание": "Весь Высоцкий — в хитроумном и энергичном изложении двух хоров",
        "Минимальная цена": "1500",
        "Ближайшее время": "19:00",
        "Ближайшая дата": "24.04.2022",
        "Жанр": "Музыкальный",
        "Рейтинг": "2.2",
        "Театр": "Большой театр кукол",
        "Ссылка на представление": "https://www.afisha.ru/performance/102509/",
        "Возрастное ограничение": "16+",
        "Адрес театра": "Некрасова, 10",
        "Продолжительность": "2 часа, без антракта",
        "Другие даты и время": -1
    },
    {
        "Название представления": "Свадьба Кречинского",
        "Описание": "Отличный актерский дуэт Евгения Александрова и Михаила Трясорукова.",
        "Минимальная цена": "1000",
        "Ближайшее время": "19:00",
        "Ближайшая дата": "24.04.2022",
        "Жанр": "Комедия",
        "Рейтинг": "7.2",
        "Театр": "Буфф",
        "Ссылка на представление": "https://www.afisha.ru/performance/76411/",
        "Возрастное ограничение": "12+",
        "Адрес театра": "Заневский просп., 26",
        "Продолжительность": "3 часа 30 минут, 1 антракт",
        "Другие даты и время": -1
    },
    {
        "Название представления": "Отцы и дети",
        "Описание": "Лирическая драма о конфликте поколений по мотивам Тургенева.",
        "Минимальная цена": "600",
        "Ближайшее время": "19:00",
        "Ближайшая дата": "18.06.2022",
        "Жанр": "Драма",
        "Рейтинг": "3.8",
        "Театр": "ТЮЗ",
        "Ссылка на представление": "https://www.afisha.ru/performance/78058/",
        "Возрастное ограничение": "12+",
        "Адрес театра": "Пионерская пл., 1",
        "Продолжительность": "2 часа 40 минут, 1 антракт",
        "Другие даты и время": -1
    },
    {
        "Название представления": "Женитьба Белугина",
        "Описание": "Брак по расчету оборачивается любовной идиллией",
        "Минимальная цена": "600",
        "Ближайшее время": "19:00",
        "Ближайшая дата": "24.05.2022",
        "Жанр": "Драма",
        "Рейтинг": "8.1",
        "Театр": "Театр-фестиваль «Балтийский дом»",
        "Ссылка на представление": "https://www.afisha.ru/performance/83293/",
        "Возрастное ограничение": "12+",
        "Адрес театра": "Александровский парк, 4",
        "Продолжительность": "-1",
        "Другие даты и время": -1
    },
    {
        "Название представления": "Шутники",
        "Описание": "Бытовой, жизнеподобный психологический театр",
        "Минимальная цена": "1000",
        "Ближайшее время": "19:00",
        "Ближайшая дата": "11.05.2022",
        "Жанр": "Драма",
        "Рейтинг": "8.1",
        "Театр": "Русская антреприза им. Андрея Миронова",
        "Ссылка на представление": "https://www.afisha.ru/performance/69518/",
        "Возрастное ограничение": "12+",
        "Адрес театра": "Большой просп. П.С., 75/35",
        "Продолжительность": "3 часа 15 минут, 1 антракт",
        "Другие даты и время": -1
    },
    {
        "Название представления": "Бременские музыканты",
        "Описание": "Всеми любимая музыкальная сказка с современными диалогами и аранжировками",
        "Минимальная цена": "500",
        "Ближайшее время": "13:00",
        "Ближайшая дата": "29.05.2022",
        "Жанр": "Детский",
        "Рейтинг": "7",
        "Театр": "Мастерская",
        "Ссылка на представление": "https://www.afisha.ru/performance/88737/",
        "Возрастное ограничение": "6+",
        "Адрес театра": "Народная, 1",
        "Продолжительность": "1 час 30 минут, без антракта",
        "Другие даты и время": -1
    },
    {
        "Название представления": "Лейтенант с острова Инишмор",
        "Описание": "Запредельно черная комедия: из трех котов выживет только один",
        "Минимальная цена": "1200",
        "Ближайшее время": "19:00",
        "Ближайшая дата": "19.05.2022",
        "Жанр": "Комедия",
        "Рейтинг": "7.2",
        "Театр": "За Черной речкой",
        "Ссылка на представление": "https://www.afisha.ru/performance/78792/",
        "Возрастное ограничение": "18+",
        "Адрес театра": "Богатырский просп., 4",
        "Продолжительность": "-1",
        "Другие даты и время": -1
    },
    {
        "Название представления": "Живой товар",
        "Описание": "Пошлый романчик перерастает в человеческую трагедию.",
        "Минимальная цена": "300",
        "Ближайшее время": "19:00",
        "Ближайшая дата": "05.05.2022",
        "Жанр": "Драма",
        "Рейтинг": "2.3",
        "Театр": "Театр им. Комиссаржевской",
        "Ссылка на представление": "https://www.afisha.ru/performance/76119/",
        "Возрастное ограничение": "14+",
        "Адрес театра": "Итальянская, 19",
        "Продолжительность": "2 часа 45 минут, 1 антракт",
        "Другие даты и время": -1
    },
    {
        "Название представления": "Сказка для непослушных медвежат",
        "Описание": "Нравоучительная сказка для дошкольников",
        "Минимальная цена": "400",
        "Ближайшее время": "11:30",
        "Ближайшая дата": "03.05.2022",
        "Жанр": "Кукольный спектакль",
        "Рейтинг": "6.5",
        "Театр": "Большой театр кукол",
        "Ссылка на представление": "https://www.afisha.ru/performance/76633/",
        "Возрастное ограничение": "0+",
        "Адрес театра": "Некрасова, 10",
        "Продолжительность": "1 час 30 минут, 1 антракт",
        "Другие даты и время": -1
    },
    {
        "Название представления": "Дон Жуан",
        "Описание": "Классическая опера в постановке радикала Юрия Александрова",
        "Минимальная цена": "700",
        "Ближайшее время": "19:00",
        "Ближайшая дата": "29.04.2022",
        "Жанр": "Опера",
        "Рейтинг": "5.3",
        "Театр": "Санкт-Петербург Опера",
        "Ссылка на представление": "https://www.afisha.ru/performance/78313/",
        "Возрастное ограничение": "16+",
        "Адрес театра": "Галерная, 33",
        "Продолжительность": "3 часа 10 минут",
        "Другие даты и время": -1
    },
    {
        "Название представления": "Ворон",
        "Описание": "Страшная сказка для взрослых с конструктивистскими аттракционами",
        "Минимальная цена": "900",
        "Ближайшее время": "19:00",
        "Ближайшая дата": "15.05.2022",
        "Жанр": "Драма",
        "Рейтинг": "7.7",
        "Театр": "Александринский театр",
        "Ссылка на представление": "https://www.afisha.ru/performance/87654/",
        "Возрастное ограничение": "16+",
        "Адрес театра": "пл. Островского, 2",
        "Продолжительность": "-1",
        "Другие даты и время": -1
    },
    {
        "Название представления": "Иисус Христос — суперзвезда",
        "Описание": "Постановка питерского театра «Рок-опера»",
        "Минимальная цена": "900",
        "Ближайшее время": "19:00",
        "Ближайшая дата": "24.04.2022",
        "Жанр": "Музыкальный",
        "Рейтинг": "8.5",
        "Театр": "ДК им. Ленсовета",
        "Ссылка на представление": "https://www.afisha.ru/performance/66149/",
        "Возрастное ограничение": "12+",
        "Адрес театра": "Каменноостровский просп., 42",
        "Продолжительность": "-1",
        "Другие даты и время": -1
    },
    {
        "Название представления": "Когда я снова стану маленьким",
        "Описание": "Энциклопедия подростковых грез и слез, упакованная в 15 чемоданов",
        "Минимальная цена": "900",
        "Ближайшее время": "18:00",
        "Ближайшая дата": "24.04.2022",
        "Жанр": "Кукольный спектакль",
        "Рейтинг": "8.3",
        "Театр": "БДТ",
        "Ссылка на представление": "https://www.afisha.ru/performance/97786/",
        "Возрастное ограничение": "6+",
        "Адрес театра": "наб. реки Фонтанки, 65",
        "Продолжительность": "1 час 30 минут, без антракта",
        "Другие даты и время": -1
    },
    {
        "Название представления": "Коварство и любовь",
        "Описание": "Выдающаийся спектакль Льва Додина по знаменитой трагедии Шиллера",
        "Минимальная цена": "900",
        "Ближайшее время": "19:00",
        "Ближайшая дата": "14.05.2022",
        "Жанр": "Драма",
        "Рейтинг": "7.4",
        "Театр": "МДТ — Театр Европы",
        "Ссылка на представление": "https://www.afisha.ru/performance/91030/",
        "Возрастное ограничение": "16+",
        "Адрес театра": "Рубинштейна, 18",
        "Продолжительность": "2 часа 15 минут, без антракта",
        "Другие даты и время": -1
    },
    {
        "Название представления": "Братья и сестры. Версия 2015",
        "Описание": "Бессмертный спектакль Льва Додина",
        "Минимальная цена": "900",
        "Ближайшее время": "14:30",
        "Ближайшая дата": "09.05.2022",
        "Жанр": "Драма",
        "Рейтинг": "8.8",
        "Театр": "МДТ — Театр Европы",
        "Ссылка на представление": "https://www.afisha.ru/performance/66218/",
        "Возрастное ограничение": "16+",
        "Адрес театра": "Рубинштейна, 18",
        "Продолжительность": " ",
        "Другие даты и время": -1
    },
    {
        "Название представления": "Дон Кихот",
        "Описание": "Веселый балет на все случаи жизни",
        "Минимальная цена": "900",
        "Ближайшее время": "19:00",
        "Ближайшая дата": "27.04.2022",
        "Жанр": "Балет",
        "Рейтинг": "8.2",
        "Театр": "Михайловский театр",
        "Ссылка на представление": "https://www.afisha.ru/performance/66506/",
        "Возрастное ограничение": "12+",
        "Адрес театра": "пл. Искусств, 1",
        "Продолжительность": "2 часа 45 минут, 2 антракта",
        "Другие даты и время": -1
    },
    {
        "Название представления": "Бесплодные усилия любви",
        "Описание": "Парадоксальный трагифарс Льва Додина о том, что юность и любовь — две вещи несовместные",
        "Минимальная цена": "900",
        "Ближайшее время": "19:00",
        "Ближайшая дата": "26.04.2022",
        "Жанр": "Драма",
        "Рейтинг": "8.3",
        "Театр": "МДТ — Театр Европы",
        "Ссылка на представление": "https://www.afisha.ru/performance/76364/",
        "Возрастное ограничение": "16+",
        "Адрес театра": "Рубинштейна, 18",
        "Продолжительность": "2 часа 15 минут, без антракта",
        "Другие даты и время": -1
    },
    {
        "Название представления": "Жизнь за царя",
        "Описание": "Театральная актуализация «дела народовольцев»",
        "Минимальная цена": "900",
        "Ближайшее время": "17:00",
        "Ближайшая дата": "30.04.2022",
        "Жанр": "Драма",
        "Рейтинг": "9.3",
        "Театр": "Karlsson Haus на Фурштатской",
        "Ссылка на представление": "https://www.afisha.ru/performance/98390/",
        "Возрастное ограничение": "16+",
        "Адрес театра": "Фурштатская, 30",
        "Продолжительность": "-1",
        "Другие даты и время": -1
    },
    {
        "Название представления": "Гамлет",
        "Описание": "Детективная драма о безуспешной борьбе с системой",
        "Минимальная цена": "900",
        "Ближайшее время": "19:00",
        "Ближайшая дата": "05.05.2022",
        "Жанр": "Драма",
        "Рейтинг": "8.1",
        "Театр": "Александринский театр",
        "Ссылка на представление": "https://www.afisha.ru/performance/80861/",
        "Возрастное ограничение": "16+",
        "Адрес театра": "пл. Островского, 2",
        "Продолжительность": "-1",
        "Другие даты и время": -1
    },
    {
        "Название представления": "Оптимистическая трагедия. Прощальный бал",
        "Описание": "Впечатляющий мэшап о последствиях 1917 года с оглядкой на весь ХХ век",
        "Минимальная цена": "900",
        "Ближайшее время": "19:00",
        "Ближайшая дата": "28.04.2022",
        "Жанр": "Драма",
        "Рейтинг": "7.3",
        "Театр": "Александринский театр",
        "Ссылка на представление": "https://www.afisha.ru/performance/201811/",
        "Возрастное ограничение": "16+",
        "Адрес театра": "пл. Островского, 2",
        "Продолжительность": "-1",
        "Другие даты и время": -1
    },
    {
        "Название представления": "Женитьба",
        "Описание": "Частная жизнь на бойком месте",
        "Минимальная цена": "900",
        "Ближайшее время": "19:00",
        "Ближайшая дата": "29.04.2022",
        "Жанр": "Драма",
        "Рейтинг": "6.9",
        "Театр": "Александринский театр",
        "Ссылка на представление": "https://www.afisha.ru/performance/75714/",
        "Возрастное ограничение": "12+",
        "Адрес театра": "пл. Островского, 2",
        "Продолжительность": "-1",
        "Другие даты и время": -1
    },
    {
        "Название представления": "Маскарад. Воспоминания будущего",
        "Описание": "Сцена Александринки как пятое измерение",
        "Минимальная цена": "900",
        "Ближайшее время": "19:00",
        "Ближайшая дата": "12.05.2022",
        "Жанр": "Драма",
        "Рейтинг": "7.9",
        "Театр": "Александринский театр",
        "Ссылка на представление": "https://www.afisha.ru/performance/99846/",
        "Возрастное ограничение": "16+",
        "Адрес театра": "пл. Островского, 2",
        "Продолжительность": "2 часа 30 минут, 1 антракт",
        "Другие даты и время": -1
    },
    {
        "Название представления": "Бабилей",
        "Описание": "Уникальная актриса Вера Быкова в моноспектакле по прозе Федора Абрамова",
        "Минимальная цена": "900",
        "Ближайшее время": "19:30",
        "Ближайшая дата": "07.05.2022",
        "Жанр": "Моноспектакль",
        "Рейтинг": "8.9",
        "Театр": "МДТ — Театр Европы",
        "Ссылка на представление": "https://www.afisha.ru/performance/86493/",
        "Возрастное ограничение": "16+",
        "Адрес театра": "Рубинштейна, 18",
        "Продолжительность": "-1",
        "Другие даты и время": -1
    },
    {
        "Название представления": "Евгений Онегин",
        "Описание": "Борис Эйфман достает из сундука спектакль про лихие 90-е",
        "Минимальная цена": "900",
        "Ближайшее время": "20:00",
        "Ближайшая дата": "30.04.2022",
        "Жанр": "Балет",
        "Рейтинг": "6.9",
        "Театр": "Александринский театр",
        "Ссылка на представление": "https://www.afisha.ru/performance/78694/",
        "Возрастное ограничение": "пл. Островского, 2",
        "Адрес театра": "пл. Островского, 2",
        "Продолжительность": "-1",
        "Другие даты и время": -1
    },
    {
        "Название представления": "Нана",
        "Описание": "Андрий Жолдак фантазирует по мотивам романа Эмиля Золя",
        "Минимальная цена": "900",
        "Ближайшее время": "19:00",
        "Ближайшая дата": "11.05.2022",
        "Жанр": "Драма",
        "Рейтинг": "7",
        "Театр": "Александринский театр. Новая сцена",
        "Ссылка на представление": "https://www.afisha.ru/performance/231175/",
        "Возрастное ограничение": "18+",
        "Адрес театра": "наб. реки Фонтанки, 49а",
        "Продолжительность": "3 часа, 1 антракт",
        "Другие даты и время": -1
    },
    {
        "Название представления": "Дом Бернарды Альбы",
        "Описание": "Адская драма неистовой материнской любви",
        "Минимальная цена": "900",
        "Ближайшее время": "19:30",
        "Ближайшая дата": "27.05.2022",
        "Жанр": "Драма",
        "Рейтинг": "7.3",
        "Театр": "МДТ — Театр Европы",
        "Ссылка на представление": "https://www.afisha.ru/performance/68901/",
        "Возрастное ограничение": "18+",
        "Адрес театра": "Рубинштейна, 18",
        "Продолжительность": "1 час 45 минут, без антракта",
        "Другие даты и время": -1
    },
    {
        "Название представления": "Лауренсия",
        "Описание": "Единственный забытый балет советского наследия, который по-настоящему стоит того, чтобы его вспомнить",
        "Минимальная цена": "900",
        "Ближайшее время": "13:00",
        "Ближайшая дата": "21.05.2022",
        "Жанр": "Балет",
        "Рейтинг": "7.7",
        "Театр": "Михайловский театр",
        "Ссылка на представление": "https://www.afisha.ru/performance/81233/",
        "Возрастное ограничение": "12+",
        "Адрес театра": "пл. Искусств, 1",
        "Продолжительность": "1 час 50 минут, 1 антракт",
        "Другие даты и время": -1
    },
    {
        "Название представления": "Преступление и наказание",
        "Описание": "Пятичасовой аккуратно осовремененный Достоевский",
        "Минимальная цена": "900",
        "Ближайшее время": "17:00",
        "Ближайшая дата": "14.05.2022",
        "Жанр": "Драма",
        "Рейтинг": "6.6",
        "Театр": "Александринский театр",
        "Ссылка на представление": "https://www.afisha.ru/performance/158543/",
        "Возрастное ограничение": "12+",
        "Адрес театра": "пл. Островского, 2",
        "Продолжительность": "-1",
        "Другие даты и время": -1
    },
    {
        "Название представления": "Литургия Zero",
        "Описание": "Антон Шагин в спектакле Валерия Фокина о страсти к игре, уничтожающей все живое",
        "Минимальная цена": "900",
        "Ближайшее время": "19:00",
        "Ближайшая дата": "13.05.2022",
        "Жанр": "Драма",
        "Рейтинг": "5.7",
        "Театр": "Александринский театр",
        "Ссылка на представление": "https://www.afisha.ru/performance/89677/",
        "Возрастное ограничение": "16+",
        "Адрес театра": "пл. Островского, 2",
        "Продолжительность": "-1",
        "Другие даты и время": -1
    },
    {
        "Название представления": "Вишневый сад",
        "Описание": "Традиционный и в то же время стопроцентно авторский Чехов",
        "Минимальная цена": "900",
        "Ближайшее время": "19:00",
        "Ближайшая дата": "13.05.2022",
        "Жанр": "Драма",
        "Рейтинг": "4.8",
        "Театр": "МДТ — Театр Европы",
        "Ссылка на представление": "https://www.afisha.ru/performance/97656/",
        "Возрастное ограничение": "16+",
        "Адрес театра": "Рубинштейна, 18",
        "Продолжительность": "3 часа, 1 антракт",
        "Другие даты и время": -1
    },
    {
        "Название представления": "Покаяние и прощение",
        "Описание": "Марионеточная фантасмагория по Пушкину — о судьбе и вере",
        "Минимальная цена": "900",
        "Ближайшее время": "19:00",
        "Ближайшая дата": "26.04.2022",
        "Жанр": "Кукольный спектакль",
        "Рейтинг": "8",
        "Театр": "Большой театр кукол",
        "Ссылка на представление": "https://www.afisha.ru/performance/85805/",
        "Возрастное ограничение": "12+",
        "Адрес театра": "Некрасова, 10",
        "Продолжительность": "1 час 50 минут",
        "Другие даты и время": -1
    },
    {
        "Название представления": "Тщетная предосторожность",
        "Описание": "Изящная сельская комедия",
        "Минимальная цена": "900",
        "Ближайшее время": "19:00",
        "Ближайшая дата": "13.05.2022",
        "Жанр": "Балет",
        "Рейтинг": "7.7",
        "Театр": "Михайловский театр",
        "Ссылка на представление": "https://www.afisha.ru/performance/68311/",
        "Возрастное ограничение": "6+",
        "Адрес театра": "пл. Искусств, 1",
        "Продолжительность": "2 часа 45 минут, 2 антракта",
        "Другие даты и время": -1
    },
    {
        "Название представления": "Блаженная Ксения. История любви",
        "Описание": "Смелая и виртуозная трактовка мифа о любимой петербургской святой",
        "Минимальная цена": "900",
        "Ближайшее время": "19:00",
        "Ближайшая дата": "27.04.2022",
        "Жанр": "Драма",
        "Рейтинг": "4.6",
        "Театр": "Александринский театр",
        "Ссылка на представление": "https://www.afisha.ru/performance/78499/",
        "Возрастное ограничение": "16+",
        "Адрес театра": "пл. Островского, 2",
        "Продолжительность": "-1",
        "Другие даты и время": -1
    },
    {
        "Название представления": "Евгений Онегин",
        "Описание": "Спектакль Андрия Жолдака: любителям милой старины просьба не беспокоиться",
        "Минимальная цена": "900",
        "Ближайшее время": "19:00",
        "Ближайшая дата": "18.05.2022",
        "Жанр": "Опера",
        "Рейтинг": "6.4",
        "Театр": "Михайловский театр",
        "Ссылка на представление": "https://www.afisha.ru/performance/91504/",
        "Возрастное ограничение": "16+",
        "Адрес театра": "пл. Искусств, 1",
        "Продолжительность": "3 часа 25 минут, 2 антракта",
        "Другие даты и время": -1
    },
    {
        "Название представления": "Мнимый больной",
        "Описание": "Лихой фарс по Мольеру с Юрием Гальцевым и Вячеславом Манучаровым",
        "Минимальная цена": "900",
        "Ближайшее время": "19:00",
        "Ближайшая дата": "04.05.2022",
        "Жанр": "Драма",
        "Рейтинг": "4",
        "Театр": "Театр эстрады им. Аркадия Райкина",
        "Ссылка на представление": "https://www.afisha.ru/performance/90764/",
        "Возрастное ограничение": "16+",
        "Адрес театра": "Б.Конюшенная, 27",
        "Продолжительность": "-1",
        "Другие даты и время": -1
    },
    {
        "Название представления": "Блаженная Ксения. История любви",
        "Описание": "Смелая и виртуозная трактовка мифа о любимой петербургской святой",
        "Минимальная цена": "900",
        "Ближайшее время": "19:00",
        "Ближайшая дата": "27.04.2022",
        "Жанр": "Драма",
        "Рейтинг": "4.6",
        "Театр": "Александринский театр",
        "Ссылка на представление": "https://www.afisha.ru/performance/78499/",
        "Возрастное ограничение": "16+",
        "Адрес театра": "пл. Островского, 2",
        "Продолжительность": "-1",
        "Другие даты и время": -1
    },
    {
        "Название представления": "Евгений Онегин",
        "Описание": "Спектакль Андрия Жолдака: любителям милой старины просьба не беспокоиться",
        "Минимальная цена": "900",
        "Ближайшее время": "19:00",
        "Ближайшая дата": "18.05.2022",
        "Жанр": "Опера",
        "Рейтинг": "6.4",
        "Театр": "Михайловский театр",
        "Ссылка на представление": "https://www.afisha.ru/performance/91504/",
        "Возрастное ограничение": "16+",
        "Адрес театра": "пл. Искусств, 1",
        "Продолжительность": "3 часа 25 минут, 2 антракта",
        "Другие даты и время": -1
    },
    {
        "Название представления": "Мнимый больной",
        "Описание": "Лихой фарс по Мольеру с Юрием Гальцевым и Вячеславом Манучаровым",
        "Минимальная цена": "900",
        "Ближайшее время": "19:00",
        "Ближайшая дата": "04.05.2022",
        "Жанр": "Драма",
        "Рейтинг": "4",
        "Театр": "Театр эстрады им. Аркадия Райкина",
        "Ссылка на представление": "https://www.afisha.ru/performance/90764/",
        "Возрастное ограничение": "16+",
        "Адрес театра": "Б.Конюшенная, 27",
        "Продолжительность": "-1",
        "Другие даты и время": -1
    },
    {
        "Название представления": "Три сестры",
        "Описание": "Пять пудов любви и повседневный трагизм в выдающемся спектакле Льва Додина по Чехову",
        "Минимальная цена": "900",
        "Ближайшее время": "19:00",
        "Ближайшая дата": "16.05.2022",
        "Жанр": "Драма",
        "Рейтинг": "2.4",
        "Театр": "МДТ — Театр Европы",
        "Ссылка на представление": "https://www.afisha.ru/performance/82203/",
        "Возрастное ограничение": "16+",
        "Адрес театра": "Рубинштейна, 18",
        "Продолжительность": "3 часа, 1 антракт",
        "Другие даты и время": -1
    },
    {
        "Название представления": "Русский и литература",
        "Описание": "Трагическая история о русском провинциальном учителе-идеалисте",
        "Минимальная цена": "900",
        "Ближайшее время": "19:30",
        "Ближайшая дата": "14.05.2022",
        "Жанр": "Драма",
        "Рейтинг": "5",
        "Театр": "МДТ — Театр Европы",
        "Ссылка на представление": "https://www.afisha.ru/performance/94990/",
        "Возрастное ограничение": "18+",
        "Адрес театра": "Рубинштейна, 18",
        "Продолжительность": "-1",
        "Другие даты и время": -1
    },
    {
        "Название представления": "Сирано де Бержерак",
        "Описание": "Постмодерн-боевик на материале классического текста",
        "Минимальная цена": "900",
        "Ближайшее время": "19:00",
        "Ближайшая дата": "24.04.2022",
        "Жанр": "Драма",
        "Рейтинг": "8.6",
        "Театр": "Александринский театр",
        "Ссылка на представление": "https://www.afisha.ru/performance/204940/",
        "Возрастное ограничение": "16+",
        "Адрес театра": "пл. Островского, 2",
        "Продолжительность": "-1",
        "Другие даты и время": -1
    },
    {
        "Название представления": "Белый. Петербург",
        "Описание": "Фантасмагорический мюзикл по роману Андрея Белого",
        "Минимальная цена": "900",
        "Ближайшее время": "19:00",
        "Ближайшая дата": "11.05.2022",
        "Жанр": "Музыкальный",
        "Рейтинг": "7.3",
        "Театр": "Театр музыкальной комедии",
        "Ссылка на представление": "https://www.afisha.ru/performance/102989/",
        "Возрастное ограничение": "16+",
        "Адрес театра": "Итальянская, 13",
        "Продолжительность": "3 часа 15 минут, 1 антракт",
        "Другие даты и время": -1
    },
    {
        "Название представления": "Дети солнца",
        "Описание": "Размышления об идеальном человеке",
        "Минимальная цена": "900",
        "Ближайшее время": "19:00",
        "Ближайшая дата": "18.05.2022",
        "Жанр": "Драма",
        "Рейтинг": "3.2",
        "Театр": "Александринский театр",
        "Ссылка на представление": "https://www.afisha.ru/performance/233405/",
        "Возрастное ограничение": "16+",
        "Адрес театра": "пл. Островского, 2",
        "Продолжительность": "2 часа, без антракта",
        "Другие даты и время": -1
    },
    {
        "Название представления": "Повелитель мух",
        "Описание": "Вторая редакция великого спектакля",
        "Минимальная цена": "900",
        "Ближайшее время": "19:00",
        "Ближайшая дата": "18.05.2022",
        "Жанр": "Драма",
        "Рейтинг": "7.2",
        "Театр": "МДТ — Театр Европы",
        "Ссылка на представление": "https://www.afisha.ru/performance/79164/",
        "Возрастное ограничение": "12+",
        "Адрес театра": "Рубинштейна, 18",
        "Продолжительность": "2 часа 10 минут, без антракта",
        "Другие даты и время": -1
    },
    {
        "Название представления": "Сильва",
        "Описание": "Спектакль Санкт-Петербургского государственного театра музыкальной комедии",
        "Минимальная цена": "900",
        "Ближайшее время": "19:00",
        "Ближайшая дата": "03.05.2022",
        "Жанр": "Оперетта",
        "Рейтинг": "5.6",
        "Театр": "Театр музыкальной комедии",
        "Ссылка на представление": "https://www.afisha.ru/performance/72819/",
        "Возрастное ограничение": "12+",
        "Адрес театра": "Итальянская, 13",
        "Продолжительность": "3 часа 15 минут, 2 антракта",
        "Другие даты и время": -1
    },
    {
        "Название представления": "Ромео и Джульетта",
        "Описание": "Битва хрупкого хореографа Дуато с балетом-монстром",
        "Минимальная цена": "900",
        "Ближайшее время": "19:00",
        "Ближайшая дата": "04.05.2022",
        "Жанр": "Балет",
        "Рейтинг": "6.9",
        "Театр": "Михайловский театр",
        "Ссылка на представление": "https://www.afisha.ru/performance/91766/",
        "Возрастное ограничение": "12+",
        "Адрес театра": "пл. Искусств, 1",
        "Продолжительность": "2 часа 30 минут, 1 антракт",
        "Другие даты и время": -1
    },
    {
        "Название представления": "Привидения",
        "Описание": "Семейная драма про то, как ложь отцов убивает детей",
        "Минимальная цена": "900",
        "Ближайшее время": "19:30",
        "Ближайшая дата": "06.05.2022",
        "Жанр": "Драма",
        "Рейтинг": "7.7",
        "Театр": "МДТ — Театр Европы",
        "Ссылка на представление": "https://www.afisha.ru/performance/83904/",
        "Возрастное ограничение": "16+",
        "Адрес театра": "Рубинштейна, 18",
        "Продолжительность": "-1",
        "Другие даты и время": -1
    },
    {
        "Название представления": "Братья Карамазовы",
        "Описание": "Постдраматический Достоевский",
        "Минимальная цена": "900",
        "Ближайшее время": "19:00",
        "Ближайшая дата": "24.05.2022",
        "Жанр": "Драма",
        "Рейтинг": "6.1",
        "Театр": "МДТ — Театр Европы",
        "Ссылка на представление": "https://www.afisha.ru/performance/232171/",
        "Возрастное ограничение": "16+",
        "Адрес театра": "Рубинштейна, 18",
        "Продолжительность": "3 часа 20 минут, 1 антракт",
        "Другие даты и время": -1
    },
    {
        "Название представления": "Мамаша Кураж и ее дети",
        "Описание": "Экзальтированная трагедия с хором в камуфляже",
        "Минимальная цена": "900",
        "Ближайшее время": "19:00",
        "Ближайшая дата": "08.05.2022",
        "Жанр": "Драма",
        "Рейтинг": "4.1",
        "Театр": "Александринский театр",
        "Ссылка на представление": "https://www.afisha.ru/performance/190189/",
        "Возрастное ограничение": "16+",
        "Адрес театра": "пл. Островского, 2",
        "Продолжительность": "-1",
        "Другие даты и время": -1
    },
    {
        "Название представления": "Трое на качелях",
        "Описание": "Мистическая комедия с внешними признаками стимпанка",
        "Минимальная цена": "900",
        "Ближайшее время": "19:00",
        "Ближайшая дата": "21.05.2022",
        "Жанр": "Драма",
        "Рейтинг": "3.1",
        "Театр": "Театр на Васильевском",
        "Ссылка на представление": "https://www.afisha.ru/performance/103544/",
        "Возрастное ограничение": "16+",
        "Адрес театра": "Средний просп. В.О., 48",
        "Продолжительность": "2 часа 40 минут, 1 антракт",
        "Другие даты и время": -1
    },
    {
        "Название представления": "Сельская честь",
        "Описание": "Постановка итальянского мастера на петербургской сцене.",
        "Минимальная цена": "900",
        "Ближайшее время": "19:00",
        "Ближайшая дата": "26.04.2022",
        "Жанр": "Опера",
        "Рейтинг": "7.8",
        "Театр": "Михайловский театр",
        "Ссылка на представление": "https://www.afisha.ru/performance/75718/",
        "Возрастное ограничение": "12+",
        "Адрес театра": "пл. Искусств, 1",
        "Продолжительность": "1 час 45 минут, 1 антракт",
        "Другие даты и время": -1
    },
    {
        "Название представления": "Русское варенье",
        "Описание": "Комедия Людмилы Улицкой на чеховские темы",
        "Минимальная цена": "900",
        "Ближайшее время": "19:00",
        "Ближайшая дата": "10.05.2022",
        "Жанр": "Драма",
        "Рейтинг": "7.2",
        "Театр": "Театр на Васильевском",
        "Ссылка на представление": "https://www.afisha.ru/performance/74889/",
        "Возрастное ограничение": "16+",
        "Адрес театра": "Средний просп. В.О., 48",
        "Продолжительность": "2 часа 15 минут, без антракта",
        "Другие даты и время": -1
    },
    {
        "Название представления": "Сказка о царе Салтане",
        "Описание": "Полет шмеля и другие музыкальные радости",
        "Минимальная цена": "900",
        "Ближайшее время": "19:00",
        "Ближайшая дата": "24.04.2022",
        "Жанр": "Опера",
        "Рейтинг": "5",
        "Театр": "Мариинский театр",
        "Ссылка на представление": "https://www.afisha.ru/performance/68091/",
        "Возрастное ограничение": "6+",
        "Адрес театра": "Театральная пл., 1",
        "Продолжительность": "-1",
        "Другие даты и время": -1
    }
]